PythonMagickWand
setup.cfg
setup.py
PythonMagickWand/__init__.py
PythonMagickWand.egg-info/PKG-INFO
PythonMagickWand.egg-info/SOURCES.txt
PythonMagickWand.egg-info/SOURCES.txt~
PythonMagickWand.egg-info/dependency_links.txt
PythonMagickWand.egg-info/entry_points.txt
PythonMagickWand.egg-info/paster_plugins.txt
PythonMagickWand.egg-info/top_level.txt
PythonMagickWand.egg-info/zip-safe