Metadata-Version: 1.0
Name: PythonMagickWand
Version: 0.2
Summary: Python wrapper for the ImageMagick wand API
Home-page: http://www.procoders.net
Author: Achim Domma
Author-email: domma@procoders.net
License: MIT
Keywords: ImageMagick
Platform: UNKNOWN
Classifier: Development Status :: 4 - Beta
Classifier: Topic :: Multimedia :: Graphics
